{
  "serviceFee": 25,
  "version": "1.0",
  "_id": "349jnfmdfmop3q9m9cf3w34f3",
  "serviceCode": "MLHA_004_05_016",
  "title": "Application For Registration As Citizen Of Botswana Of Person Under 21",
  "description": {
    "short": "An application for the registration of a person under 21 as a citizen of Botswana.",
    "long": "This is an application for the registration of a person under 21 as a citizen of Botswana. The application is designed for individuals who meet the eligibility criteria to acquire Botswana citizenship before reaching the age of 21. ",
    "act": "Citizenship Act (Act 9 of 1998)"
  },
  "rating": 4,
  "favourite": true,
  "trending_weight": 0.72,
  "registeredDate": "2023-05-15",
  "recommended": false,
  "icon": "mdi:account",
  "shortName": "Registration of Citizenship",
  "category": "Citizenship",
  "ministry": "Ministry of Labour and Home Affairs",
  "department": "Department of Labour and Social Security",
  "payments": [
    {
      "id": 1,
      "amount": 25,
      "currency": "BWP",
      "description": "Application fee"
    }
  ],
  "form": [
    {
      "title": "APPLICANT DETAILS",
      "description":"APPLICANT PERSONAL DETAILS",
      "fields": [
        {
          "fieldName": "fullNameSurname",
          "fieldLabel": "Full Name (Surname)",
          "description": "The surname or last name of the applicant.",
          "fieldType": "ShortText",
          "hint": "",
          "transformer": [],
          "endpoint_parameter": false,
          "tooltip": "",
          "options": [],
          "breakpoints": {},
          "dependencies": {},
          "dataTableData": {},
          "endpoint": "",
          "mandatory": true,
          "disabled": false,
          "mimeTypes": []
        },
        {
          "fieldName": "firstName",
          "fieldLabel": "First Name",
          "description": "The first name of the applicant.",
          "fieldType": "ShortText",
          "hint": "",
          "transformer": [],
          "endpoint_parameter": false,
          "tooltip": "",
          "options": [],
          "breakpoints": {},
          "dependencies": {},
          "dataTableData": {},
          "endpoint": "",
          "mandatory": true,
          "disabled": false,
          "mimeTypes": []
        },
        {
          "fieldName": "middleName",
          "fieldLabel": "Middle Name",
          "description": "The middle name of the applicant.",
          "fieldType": "ShortText",
          "hint": "",
          "transformer": [],
          "endpoint_parameter": false,
          "tooltip": "",
          "options": [],
          "breakpoints": {},
          "dependencies": {},
          "dataTableData": {},
          "endpoint": "",
          "mandatory": true,
          "disabled": false,
          "mimeTypes": []
        },
        {
          "fieldName": "previousMaidenSurname",
          "fieldLabel": "Previous/Maiden Surname",
          "description": "The previous or maiden surname of the applicant.",
          "fieldType": "ShortText",
          "hint": "",
          "transformer": [],
          "endpoint_parameter": false,
          "tooltip": "",
          "options": [],
          "breakpoints": {},
          "dependencies": {},
          "dataTableData": {},
          "endpoint": "",
          "mandatory": true,
          "disabled": false,
          "mimeTypes": []
        },
        {
          "fieldName": "postalAddressTownVillage",
          "fieldLabel": "Postal Address (Town/Village)",
          "description": "The town or village of the applicant's postal address.",
          "fieldType": "ShortText",
          "hint": "",
          "transformer": [],
          "endpoint_parameter": false,
          "tooltip": "",
          "options": [],
          "breakpoints": {},
          "dependencies": {},
          "dataTableData": {},
          "endpoint": "",
          "mandatory": true,
          "disabled": false,
          "mimeTypes": []
        },
        {
          "fieldName": "postOfficeLocation",
          "fieldLabel": "Post Office Location",
          "description": "The location of the post office for the applicant's postal address.",
          "fieldType": "ShortText",
          "hint": "",
          "transformer": [],
          "endpoint_parameter": false,
          "tooltip": "",
          "options": [],
          "breakpoints": {},
          "dependencies": {},
          "dataTableData": {},
          "endpoint": "",
          "mandatory": true,
          "disabled": false,
          "mimeTypes": []
        },
        {
          "fieldName": "poBox",
          "fieldLabel": "P O Box",
          "description": "The post office box number of the applicant.",
          "fieldType": "ShortText",
          "hint": "",
          "transformer": [],
          "endpoint_parameter": false,
          "tooltip": "",
          "options": [],
          "breakpoints": {},
          "dependencies": {},
          "dataTableData": {},
          "endpoint": "",
          "mandatory": true,
          "disabled": false,
          "mimeTypes": []
        },
        {
          "fieldName": "residentialAddressTownVillage",
          "fieldLabel": "Residential Address (Town/Village)",
          "description": "The town or village of the applicant's residential address.",
          "fieldType": "ShortText",
          "hint": "",
          "transformer": [],
          "endpoint_parameter": false,
          "tooltip": "",
          "options": [],
          "breakpoints": {},
          "dependencies": {},
          "dataTableData": {},
          "endpoint": "",
          "mandatory": true,
          "disabled": false,
          "mimeTypes": []
        },
        {
          "fieldName": "plotHouseNumber",
          "fieldLabel": "Plot House Number",
          "description": "The plot or house number of the applicant's residential address.",
          "fieldType": "ShortText",
          "hint": "",
          "transformer": [],
          "endpoint_parameter": false,
          "tooltip": "",
          "options": [],
          "breakpoints": {},
          "dependencies": {},
          "dataTableData": {},
          "endpoint": "",
          "mandatory": true,
          "disabled": false,
          "mimeTypes": []
        },
        {
          "fieldName": "streetWard",
          "fieldLabel": "Street/Ward",
          "description": "The street or ward of the applicant's residential address.",
          "fieldType": "ShortText",
          "hint": "",
          "transformer": [],
          "endpoint_parameter": false,
          "tooltip": "",
          "options": [],
          "breakpoints": {},
          "dependencies": {},
          "dataTableData": {},
          "endpoint": "",
          "mandatory": true,
          "disabled": false,
          "mimeTypes": []
        },
      
        {
          "fieldName": "email",
          "fieldLabel": "Email",
          "description": "The email address of the applicant.",
          "fieldType": "Email",
          "hint": "",
          "transformer": [],
          "endpoint_parameter": false,
          "tooltip": "",
          "options": [],
          "breakpoints": {},
          "dependencies": {},
          "dataTableData": {},
          "endpoint": "",
          "mandatory": true,
          "disabled": false,
          "mimeTypes": []
        },
        {
          "fieldName": "sms",
          "fieldLabel": "SMS",
          "description": "The SMS or mobile phone number of the applicant.",
          "fieldType": "PhoneNumber",
          "hint": "",
          "transformer": [],
          "endpoint_parameter": false,
          "tooltip": "",
          "options": [],
          "breakpoints": {},
          "dependencies": {},
          "dataTableData": {},
          "endpoint": "",
          "mandatory": true,
          "disabled": false,
          "mimeTypes": []
        }
      ]
    },
    {
      "title": "PART 2: PARTICULARS IN RELATION TO CHILD",
      "fields": [
        {
          "fieldName": "fullNameSurname",
          "fieldLabel": "Full Name (Surname)",
          "hint": "",
          "fieldType": "ShortText",
          "transformer": [],
          "endpoint_parameter": false,
          "description": "The full name of the child's surname.",
          "tooltip": "",
          "options": [],
          "breakpoints": {},
          "dependancies": [],
          "dataTableData": {},
          "endpoint": "",
          "mandatory": true,
          "disabled": false,
          "mimeTypes": []
        },
        {
          "fieldName": "firstName",
          "fieldLabel": "First Name",
          "hint": "",
          "fieldType": "ShortText",
          "transformer": [],
          "endpoint_parameter": false,
          "description": "The first name of the child.",
          "tooltip": "",
          "options": [],
          "breakpoints": {},
          "dependancies": [],
          "dataTableData": {},
          "endpoint": "",
          "mandatory": true,
          "disabled": false,
          "mimeTypes": []
        },
        {
          "fieldName": "previousMaidenSurname",
          "fieldLabel": "Previous/Maiden Surname",
          "hint": "",
          "fieldType": "ShortText",
          "transformer": [],
          "endpoint_parameter": false,
          "description": "The previous or maiden surname of the child (if applicable).",
          "tooltip": "",
          "options": [],
          "breakpoints": {},
          "dependancies": [],
          "dataTableData": {},
          "endpoint": "",
          "mandatory": true,
          "disabled": false,
          "mimeTypes": []
        },
        {
          "fieldName": "maritalStatus",
          "fieldLabel": "Marital Status",
          "hint": "",
          "fieldType": "Dropdown",
          "transformer": [],
          "endpoint_parameter": false,
          "description": "The marital status of the child.",
          "tooltip": "",
          "options": ["Single", "Married", "Divorced", "Widowed", "Separated"],
          "breakpoints": {},
          "dependancies": [],
          "dataTableData": {},
          "endpoint": "",
          "mandatory": true,
          "disabled": false,
          "mimeTypes": []
        },
        {
          "fieldName": "sex",
          "fieldLabel": "Sex",
          "hint": "",
          "fieldType": "Dropdown",
          "transformer": [],
          "endpoint_parameter": false,
          "description": "The sex of the child.",
          "tooltip": "",
          "options": ["Male", "Female"],
          "breakpoints": {},
          "dependancies": [],
          "dataTableData": {},
          "endpoint": "",
          "mandatory": true,
          "disabled": false,
          "mimeTypes": []
        },
        {
          "fieldName": "countryOfBirth",
          "fieldLabel": "Country of Birth",
          "hint": "",
          "fieldType": "ShortText",
          "transformer": [],
          "endpoint_parameter": false,
          "description": "The country of birth of the child.",
          "tooltip": "",
          "options": [
            
            "Afghanistan",
            "Albania",
            "Algeria",
            "Andorra",
            "Angola",
            "Antigua and Barbuda",
            "Argentina",
            "Armenia",
            "Australia",
            "Austria",
            "Azerbaijan",
            "Bahamas",
            "Bahrain",
            "Bangladesh",
            "Barbados",
            "Belarus",
            "Belgium",
            "Belize",
            "Benin",
            "Bhutan",
            "Bolivia",
            "Bosnia and Herzegovina",
            "Botswana",
            "Brazil",
            "Brunei",
            "Bulgaria",
            "Burkina Faso",
            "Burundi",
            "Cabo Verde",
            "Cambodia",
            "Cameroon",
            "Canada",
            "Central African Republic",
            "Chad",
            "Chile",
            "China",
            "Colombia",
            "Comoros",
            "Congo",
            "Costa Rica",
            "Croatia",
            "Cuba",
            "Cyprus",
            "Czech Republic",
            "Denmark",
            "Djibouti",
            "Dominica",
            "Dominican Republic",
            "East Timor",
            "Ecuador",
            "Egypt",
            "El Salvador",
            "Equatorial Guinea",
            "Eritrea",
            "Estonia",
            "Eswatini",
            "Ethiopia",
            "Fiji",
            "Finland",
            "France",
            "Gabon",
            "Gambia",
            "Georgia",
            "Germany",
            "Ghana",
            "Greece",
            "Grenada",
            "Guatemala",
            "Guinea",
            "Guinea-Bissau",
            "Guyana",
            "Haiti",
            "Honduras",
            "Hungary",
            "Iceland",
            "India",
            "Indonesia",
            "Iran",
            "Iraq",
            "Ireland",
            "Israel",
            "Italy",
            "Jamaica",
            "Japan",
            "Jordan",
            "Kazakhstan",
            "Kenya",
            "Kiribati",
            "Korea, North",
            "Korea, South",
            "Kosovo",
            "Kuwait",
            "Kyrgyzstan",
            "Laos",
            "Latvia",
            "Lebanon",
            "Lesotho",
            "Liberia",
            "Libya",
            "Liechtenstein",
            "Lithuania",
            "Luxembourg",
            "Madagascar",
            "Malawi",
            "Malaysia",
            "Maldives",
            "Mali",
            "Malta",
            "Marshall Islands",
            "Mauritania",
            "Mauritius",
            "Mexico",
            "Micronesia",
            "Moldova",
            "Monaco",
            "Mongolia",
            "Montenegro",
            "Morocco",
            "Mozambique",
            "Myanmar",
            "Namibia",
            "Nauru",
            "Nepal",
            "Netherlands",
            "New Zealand",
            "Nicaragua",
            "Niger",
            "Nigeria",
            "North Macedonia",
            "Norway",
            "Oman",
            "Pakistan",
            "Palau",
            "Palestine",
            "Panama",
            "Papua New Guinea",
            "Paraguay",
            "Peru",
            "Philippines",
            "Poland",
            "Portugal",
            "Qatar",
            "Romania",
            "Russia",
            "Rwanda",
            "Saint Kitts and Nevis",
            "Saint Lucia",
            "Saint Vincent and the Grenadines",
            "Samoa",
            "San Marino",
            "Sao Tome and Principe",
            "Saudi Arabia",
            "Senegal",
            "Serbia",
            "Seychelles",
            "Sierra Leone",
            "Singapore",
            "Slovakia",
            "Slovenia",
            "Solomon Islands",
            "Somalia",
            "South Africa",
            "South Sudan",
            "Spain",
            "Sri Lanka",
            "Sudan",
            "Suriname",
            "Sweden",
            "Switzerland",
            "Syria",
            "Taiwan",
            "Tajikistan",
            "Tanzania",
            "Thailand",
            "Togo",
            "Tonga",
            "Trinidad and Tobago",
            "Tunisia",
            "Turkey",
            "Turkmenistan",
            "Tuvalu",
            "Uganda",
            "Ukraine",
            "United Arab Emirates",
            "United Kingdom",
            "United States",
            "Uruguay",
            "Uzbekistan",
            "Vanuatu",
            "Vatican City",
            "Venezuela",
            "Vietnam",
            "Yemen",
            "Zambia",
            "Zimbabwe"
          ],
          "breakpoints": {},
          "dependancies": [],
          "dataTableData": {},
          "endpoint": "",
          "mandatory": true,
          "disabled": false,
          "mimeTypes": []
        },
        {
          "fieldName": "placeOfBirth",
          "fieldLabel": "Place of Birth",
          "hint": "",
          "fieldType": "ShortText",
          "transformer": [],
          "endpoint_parameter": false,
          "description": "The place of birth of the child.",
          "tooltip": "",
          "options": [],
          "breakpoints": {},
          "dependancies": [],
          "dataTableData": {},
          "endpoint": "",
          "mandatory": true,
          "disabled": false,
          "mimeTypes": []
        },
        {
          "fieldName": "dateOfBirth",
          "fieldLabel": "Date of Birth",
          "hint": "",
          "fieldType": "Date",
          "transformer": [],
          "endpoint_parameter": false,
          "description": "The date of birth of the child.",
          "tooltip": "",
          "options": [],
          "breakpoints": {},
          "dependancies": [],
          "dataTableData": {},
          "endpoint": "",
          "mandatory": true,
          "disabled": false,
          "mimeTypes": []
        },
        {
          "fieldName": "courtDesignationLocation",
          "fieldLabel": "Designation and Location of Court by which an Adoption Order was Granted",
          "hint": "",
          "fieldType": "ShortText",
          "transformer": [],
          "endpoint_parameter": false,
          "description": "The designation and location of the court by which an adoption order was granted.",
          "tooltip": "",
          "options": [],
          "breakpoints": {},
          "dependancies": [],
          "dataTableData": {},
          "endpoint": "",
          "mandatory": true,
          "disabled": false,
          "mimeTypes": []
        },
        {
          "fieldName": "designation",
          "fieldLabel": "Designation",
          "hint": "",
          "fieldType": "ShortText",
          "transformer": [],
          "endpoint_parameter": false,
          "description": "The designation of the applicant.",
          "tooltip": "",
          "options": [],
          "breakpoints": {},
          "dependancies": [],
          "dataTableData": {},
          "endpoint": "",
          "mandatory": true,
          "disabled": false,
          "mimeTypes": []
        },
        {
          "fieldName": "location",
          "fieldLabel": "Location",
          "hint": "",
          "fieldType": "ShortText",
          "transformer": [],
          "endpoint_parameter": false,
          "description": "The location of the applicant.",
          "tooltip": "",
          "options": [],
          "breakpoints": {},
          "dependancies": [],
          "dataTableData": {},
          "endpoint": "",
          "mandatory": true,
          "disabled": false,
          "mimeTypes": []
        },
        {
          "fieldName": "presentPostalAddress",
          "fieldLabel": "Present Postal Address (Town/Village)",
          "hint": "",
          "fieldType": "ShortText",
          "transformer": [],
          "endpoint_parameter": false,
          "description": "The present postal address of the applicant (town/village).",
          "tooltip": "",
          "options": [],
          "breakpoints": {},
          "dependancies": [],
          "dataTableData": {},
          "endpoint": "",
          "mandatory": true,
          "disabled": false,
          "mimeTypes": []
        },
        {
          "fieldName": "poBox",
          "fieldLabel": "PO Box",
          "hint": "",
          "fieldType": "ShortText",
          "transformer": [],
          "endpoint_parameter": false,
          "description": "The PO Box of the applicant.",
          "tooltip": "",
          "options": [],
          "breakpoints": {},
          "dependancies": [],
          "dataTableData": {},
          "endpoint": "",
          "mandatory": true,
          "disabled": false,
          "mimeTypes": []
        },
        {
          "fieldName": "postOfficeLocation",
          "fieldLabel": "Post Office Location",
          "description": "The location of the post office for the applicant's postal address",
          "hint": "",
          "fieldType": "ShortText",
          "transformer": [],
          "endpointParameter": false,
          "tooltip": "",
          "options": [],
          "breakpoints": {},
          "dependencies": [],
          "dataTableData": {},
          "endpoint": "",
          "mandatory": true,
          "disabled": false,
          "mimeTypes": []
        },
        {
          "fieldName": "presentResidentialAddress",
          "fieldLabel": "Present Residential Address (Town/Village)",
          "description": "The present residential address of the applicant (town/village)",
          "hint": "",
          "fieldType": "ShortText",
          "transformer": [],
          "endpointParameter": false,
          "tooltip": "",
          "options": [],
          "breakpoints": {},
          "dependencies": [],
          "dataTableData": {},
          "endpoint": "",
          "mandatory": true,
          "disabled": false,
          "mimeTypes": []
        },
        {
          "fieldName": "plotHouseNumber",
          "fieldLabel": "Plot House Number",
          "description": "The plot or house number of the applicant",
          "hint": "",
          "fieldType": "ShortText",
          "transformer": [],
          "endpointParameter": false,
          "tooltip": "",
          "options": [],
          "breakpoints": {},
          "dependencies": [],
          "dataTableData": {},
          "endpoint": "",
          "mandatory": true,
          "disabled": false,
          "mimeTypes": []
        },
        {
          "fieldName": "streetWard",
          "fieldLabel": "Street/Ward",
          "description": "The street or ward of the applicant's address",
          "hint": "",
          "fieldType": "ShortText",
          "transformer": [],
          "endpointParameter": false,
          "tooltip": "",
          "options": [],
          "breakpoints": {},
          "dependencies": [],
          "dataTableData": {},
          "endpoint": "",
          "mandatory": true,
          "disabled": false,
          "mimeTypes": []
        },
        {
          "fieldName": "occupation",
          "fieldLabel": "Occupation",
          "description": "The occupation of the applicant",
          "hint": "",
          "fieldType": "ShortText",
          "transformer": [],
          "endpointParameter": false,
          "tooltip": "",
          "options": [],
          "breakpoints": {},
          "dependencies": [],
          "dataTableData": {},
          "endpoint": "",
          "mandatory": true,
          "disabled": false,
          "mimeTypes": []
        },
        {
          "fieldName": "qualifications",
          "fieldLabel": "Qualifications",
          "description": "The qualifications of the applicant",
          "hint": "",
          "fieldType": "Dropdown",
          "transformer": [],
          "endpointParameter": false,
          "tooltip": "",
          "options": [
            "High School Diploma",
            "Bachelor's Degree",
            "Master's Degree",
            "PhD",
            "Associate Degree",
            "Professional Certification",
            "Vocational Training",
            "GED (General Educational Development)",
            "Online Courses",
            "Bootcamp Certification",
            "Trade School Certification",
            "Postgraduate Diploma",
            "Licenses"
          ],
          "breakpoints": {},
          "dependencies": [],
          "dataTableData": {},
          "endpoint": "",
          "mandatory": true,
          "disabled": false,
          "mimeTypes": []
        },
        {
          "fieldName": "citizenshipAtBirth",
          "fieldLabel": "Citizenship at Birth",
          "description": "The citizenship status of the applicant at birth",
          "hint": "",
          "fieldType": "ShortText",
          "transformer": [],
          "endpointParameter": false,
          "tooltip": "",
          "options": [],
          "breakpoints": {},
          "dependencies": [],
          "dataTableData": {},
          "endpoint": "",
          "mandatory": true,
          "disabled": false,
          "mimeTypes": []
        },
        {
          "fieldName": "presentCitizenship",
          "fieldLabel": "Present Citizenship (if different)",
          "description": "The present citizenship status of the applicant (if different from citizenship at birth)",
          "hint": "",
          "fieldType": "ShortText",
          "transformer": [],
          "endpointParameter": false,
          "tooltip": "",
          "options": [],
          "breakpoints": {},
          "dependencies": [],
          "dataTableData": {},
          "endpoint": "",
          "mandatory": true,
          "disabled": false,
          "mimeTypes": []
        },
        {
          "fieldName": "circumstancesLostCitizenship",
          "fieldLabel": "If not present citizenship, circumstances under which it was lost",
          "description": "The circumstances under which the applicant lost their previous citizenship, if they don't currently hold it",
          "hint": "",
          "fieldType": "LongText",
          "transformer": [],
          "endpointParameter": false,
          "tooltip": "",
          "options": [],
          "breakpoints": {},
          "dependencies": [],
          "dataTableData": {},
          "endpoint": "",
          "mandatory": false,
          "disabled": false,
          "mimeTypes": []
        },
        {
          "fieldName": "fullNameOfMotherFather",
          "fieldLabel": "Full Name of Mother/Father (if not applicant)",
          "hint": "",
          "fieldType": "ShortText",
          "transformer": [],
          "endpointParameter": false,
          "description": "The full name of the mother or father if they are not the applicant",
          "tooltip": "",
          "options": [],
          "breakpoints": {},
          "dependencies": [],
          "dataTableData": {},
          "endpoint": "",
          "mandatory": false,
          "disabled": false,
          "mimeTypes": []
        },
        {
          "fieldName": "surname",
          "fieldLabel": "Surname",
          "description": "The surname of the applicant",
          "hint": "",
          "fieldType": "ShortText",
          "transformer": [],
          "endpointParameter": false,
          "tooltip": "",
          "options": [],
          "breakpoints": {},
          "dependencies": [],
          "dataTableData": {},
          "endpoint": "",
          "mandatory": false,
          "disabled": false,
          "mimeTypes": []
        },
        {
          "fieldName": "firstName",
          "fieldLabel": "First Name",
          "description": "The first name of the applicant",
          "hint": "",
          "fieldType": "ShortText",
          "transformer": [],
          "endpointParameter": false,
          "tooltip": "",
          "options": [],
          "breakpoints": {},
          "dependencies": [],
          "dataTableData": {},
          "endpoint": "",
          "mandatory": false,
          "disabled": false,
          "mimeTypes": []
        },
        {
          "fieldName": "middleName",
          "fieldLabel": "Middle Name",
          "description": "The middle name of the applicant",
          "hint": "",
          "fieldType": "ShortText",
          "transformer": [],
          "endpointParameter": false,
          "tooltip": "",
          "options": [],
          "breakpoints": {},
          "dependencies": [],
          "dataTableData": {},
          "endpoint": "",
          "mandatory": false,
          "disabled": false,
          "mimeTypes": []
        },
        {
          "fieldName": "previousMaidenSurname",
          "fieldLabel": "Previous/Maiden Surname",
          "description": "The previous or maiden surname of the applicant.",
          "fieldType": "ShortText",
          "hint": "",
          "transformer": [],
          "endpoint_parameter": false,
          "tooltip": "",
          "options": [],
          "breakpoints": {},
          "dependencies": {},
          "dataTableData": {},
          "endpoint": "",
          "mandatory": true,
          "disabled": false,
          "mimeTypes": []
        },
        {
          "fieldName": "presentResidentialAddress",
          "fieldLabel": "Present Residential Address (Town/Village)",
          "description": "The present residential address of the applicant (town/village)",
          "hint": "",
          "fieldType": "ShortText",
          "transformer": [],
          "endpointParameter": false,
          "tooltip": "",
          "options": [],
          "breakpoints": {},
          "dependencies": [],
          "dataTableData": {},
          "endpoint": "",
          "mandatory": true,
          "disabled": false,
          "mimeTypes": []
        },
        {
          "fieldName": "plotHouseNumber",
          "fieldLabel": "Plot House Number",
          "description": "The plot or house number of the applicant",
          "hint": "",
          "fieldType": "ShortText",
          "transformer": [],
          "endpointParameter": false,
          "tooltip": "",
          "options": [],
          "breakpoints": {},
          "dependencies": [],
          "dataTableData": {},
          "endpoint": "",
          "mandatory": true,
          "disabled": false,
          "mimeTypes": []
        },
        {
          "fieldName": "streetWard",
          "fieldLabel": "Street/Ward",
          "description": "The street or ward of the applicant's address",
          "hint": "",
          "fieldType": "ShortText",
          "transformer": [],
          "endpointParameter": false,
          "tooltip": "",
          "options": [],
          "breakpoints": {},
          "dependencies": [],
          "dataTableData": {},
          "endpoint": "",
          "mandatory": true,
          "disabled": false,
          "mimeTypes": []
        },
        {
          "fieldName": "poBox",
          "fieldLabel": "PO Box",
          "hint": "",
          "fieldType": "ShortText",
          "transformer": [],
          "endpoint_parameter": false,
          "description": "The PO Box of the applicant.",
          "tooltip": "",
          "options": [],
          "breakpoints": {},
          "dependancies": [],
          "dataTableData": {},
          "endpoint": "",
          "mandatory": true,
          "disabled": false,
          "mimeTypes": []
        }
      ]
    },
    {
      "title": "ATTACHMENTS",
      "description": "REQUIRED ATTACHMENTS",
      "fields": [
        {
          "fieldName": "passportPhotos",
          "fieldLabel": "Passport photos",
          "hint": "",
          "fieldType": "Attachment",
          "transformer": [],
          "endpoint_parameter": false,
          "description": "Please upload two passport photos",
          "tooltip": "",
          "options": [],
          "breakpoints": {},
          "dependencies": [],
          "dataTableData": {},
          "endpoint": "",
          "mandatory": false,
          "disabled": false,
          "mimeTypes": []
        },
        {
          "fieldName": "policeReport",
          "fieldLabel": "Police Report for children over 16 years",
          "hint": "",
          "fieldType": "Attachment",
          "transformer": [],
          "endpoint_parameter": false,
          "description": "Please upload a copy of Police Report",
          "tooltip": "",
          "options": [],
          "breakpoints": {},
          "dependencies": [],
          "dataTableData": {},
          "endpoint": "",
          "mandatory": false,
          "disabled": false,
          "mimeTypes": []
        },
        {
          "fieldName": "copyOfBirthCertificate",
          "fieldLabel": "Copy of birth certificate",
          "hint": "",
          "fieldType": "Attachment",
          "transformer": [],
          "endpoint_parameter": false,
          "description": "Please upload a copy of your birth certificate",
          "tooltip": "",
          "options": [],
          "breakpoints": {},
          "dependencies": [],
          "dataTableData": {},
          "endpoint": "",
          "mandatory": false,
          "disabled": false,
          "mimeTypes": []
        },
        {
          "fieldName": "ParentsDetailsOmang",
          "fieldLabel": "Parents' details (Omang)",
          "hint": "",
          "fieldType": "Attachment",
          "transformer": [],
          "endpoint_parameter": false,
          "description": "Please upload a copy of your parents' Omang (National ID)",
          "tooltip": "",
          "options": [],
          "breakpoints": {},
          "dependencies": [],
          "dataTableData": {},
          "endpoint": "",
          "mandatory": false,
          "disabled": false,
          "mimeTypes": []
        },
        {
          "fieldName": "parentMarriageCertificate",
          "fieldLabel": "Parents Marriage Certificate",
          "hint": "",
          "fieldType": "Attachment",
          "transformer": [],
          "endpoint_parameter": false,
          "description": "Please upload a copy of parents marriage certificate",
          "tooltip": "",
          "options": [],
          "breakpoints": {},
          "dependencies": [],
          "dataTableData": {},
          "endpoint": "",
          "mandatory": false,
          "disabled": false,
          "mimeTypes": []
        },
        {
          "fieldName": "residencePermit",
          "fieldLabel": "Residence Permit",
          "hint": "",
          "fieldType": "Attachment",
          "transformer": [],
          "endpoint_parameter": false,
          "description": "",
          "tooltip": "Please upload a copy of residence permit",
          "options": [],
          "breakpoints": {},
          "dependencies": [],
          "dataTableData": {},
          "endpoint": "",
          "mandatory": false,
          "disabled": false,
          "mimeTypes": []
        }
      ]
    }
  ]
}
