{
    "version": "1.0",
    "code": "MLGRD_008_10_007",
    "name": "Additional Dog License",
    "type": "License",
    "mode":"default",
    "hasValidity": true,
    "hasValidUntil": true,
    "validity": 365,
    "period": "Days",
    "generate": [
      {
        "fieldName": "conditionsTitle",
        "defaultValue": "",
        "fieldLabel": "Conditions title",
        "enabled": false,
        "fieldType": "ShortText",
        "fieldDescription": "",
        "options": [],
        "mandatory": true
      },
      {
        "fieldName": "conditions",
        "defaultValue": "",
        "fieldLabel": "Conditions",
        "enabled": false,
        "fieldType": "LongText",
        "fieldDescription": "",
        "options": [],
        "mandatory": true
      }
  ],
  "issue": [
      {
        "fieldName": "notificationMessage",
        "defaultValue": "Your dog license permit has been issued. Please print this page and present it to the relevant authorities.",
        "fieldLabel": "Notification Message",
        "fieldType": "LongText",
        "fieldDescription": "",
        "options": [],
        "mandatory": true
      }
  ],
  "conditions": true,
    "department": "Gaborone City Council",
    "title": "Dog",
    "suffix": "DG"
}